Metadata-Version: 1.1
Name: tfds-defect-detection
Version: 1.0.0
Summary: TensorFlow Datasets for Defect Detection
Home-page: https://github.com/thetoby9944/tfds_defect_detection
Author: thetoby9944
Author-email: thetoby@web.de
License: UNKNOWN
Platform: UNKNOWN
Classifier: Development Status :: 4 - Beta
Classifier: Intended Audience :: Science/Research
Classifier: Intended Audience :: Developers
Classifier: Programming Language :: Python :: 3
Classifier: Programming Language :: Python :: 3.7
Classifier: Programming Language :: Python :: 3.8
Classifier: Programming Language :: Python :: 3.9
Classifier: License :: OSI Approved :: GNU Affero General Public License v3 or later (AGPLv3+)
